{
  "$schema": "https://developer.microsoft.com/json-schemas/fabric/item/report/definition/visualContainer/2.10.0/schema.json",
  "name": "d9f8e9f7e3a302be0a16",
  "position": {
    "x": 215.27272727272728,
    "y": 0,
    "z": 1000,
    "height": 269.09090909090907,
    "width": 162.90909090909091,
    "tabOrder": 1000
  },
  "visual": {
    "visualType": "slicer",
    "query": {
      "queryState": {
        "Values": {
          "projections": [
            {
              "field": {
                "Column": {
                  "Expression": {
                    "SourceRef": {
                      "Entity": "DIM_CROP"
                    }
                  },
                  "Property": "CROP_NAME"
                }
              },
              "queryRef": "DIM_CROP.CROP_NAME",
              "nativeQueryRef": "CROP_NAME",
              "active": true
            }
          ]
        }
      }
    },
    "objects": {
      "data": [
        {
          "properties": {
            "mode": {
              "expr": {
                "Literal": {
                  "Value": "'Basic'"
                }
              }
            }
          }
        }
      ]
    },
    "drillFilterOtherVisuals": true
  }
}